zeddo/__init__.py
zeddo/news.py
zeddo-0.2.0.dist-info/LICENSE
zeddo-0.2.0.dist-info/METADATA
zeddo-0.2.0.dist-info/WHEEL
zeddo-0.2.0.dist-info/entry_points.txt
zeddo-0.2.0.dist-info/top_level.txt
zeddo-0.2.0.dist-info/RECORD
