Metadata-Version: 2.1
Name: zeddo
Version: 0.2.0
Summary: News CLI for lazy people
Home-page: http://github.com/clabe45/zeddo
Author: Caleb Sacks
License: GPLv3
Keywords: cli news current events tool
Platform: UNKNOWN
Classifier: Development Status :: 3 - Alpha
Classifier: Environment :: Console
Classifier: Intended Audience :: Developers
Classifier: License :: OSI Approved :: GNU General Public License v3 (GPLv3)
Classifier: Operating System :: MacOS :: MacOS X
Classifier: Operating System :: Microsoft :: Windows
Classifier: Operating System :: POSIX
Classifier: Programming Language :: Python
Classifier: Topic :: Internet
Classifier: Topic :: Office/Business :: News/Diary
Requires-Dist: click
Requires-Dist: requests
Requires-Dist: click-config-file
Requires-Dist: toml
